django_flatpickr/__init__.py
django_flatpickr/_base.py
django_flatpickr/_config.py
django_flatpickr/_media.py
django_flatpickr/py.typed
django_flatpickr/schemas.py
django_flatpickr/settings.py
django_flatpickr/static/django_flatpickr/js/django-flatpickr.js
django_flatpickr/templates/django_flatpickr/input.html
django_flatpickr/widgets.py
django_flatpickr-2.0.2.dist-info/LICENSE
django_flatpickr-2.0.2.dist-info/METADATA
django_flatpickr-2.0.2.dist-info/WHEEL
django_flatpickr-2.0.2.dist-info/RECORD
