Metadata-Version: 2.1
Name: django-flatpickr
Version: 2.0.2
Summary: Flatpickr based DatePickerInput, TimePickerInput and DateTimePickerInput with date-range-picker functionality for django >= 2.0
Home-page: https://github.com/monim67/django-flatpickr
License: MIT
Keywords: django,flatpickr,date-picker,time-picker,datetime-picker,date-range-picker
Author: Munim Munna
Author-email: 6266677+monim67@users.noreply.github.com
Requires-Python: >=3.8,<4.0
Classifier: Development Status :: 5 - Production/Stable
Classifier: Environment :: Web Environment
Classifier: Framework :: Django
Classifier: Framework :: Django :: 2.0
Classifier: Framework :: Django :: 3.0
Classifier: Framework :: Django :: 4.0
Classifier: Framework :: Django :: 5.0
Classifier: Intended Audience :: Developers
Classifier: License :: OSI Approved :: MIT License
Classifier: Operating System :: OS Independent
Classifier: Programming Language :: Python :: 3
Classifier: Programming Language :: Python :: 3.8
Classifier: Programming Language :: Python :: 3.9
Classifier: Programming Language :: Python :: 3.10
Classifier: Programming Language :: Python :: 3.11
Classifier: Programming Language :: Python :: 3.12
Classifier: Topic :: Software Development :: Libraries
Classifier: Topic :: Utilities
Requires-Dist: Django (>=2,<6)
Requires-Dist: pydantic (>=2,<3)
Requires-Dist: pydantic-settings
Requires-Dist: typing-extensions
Project-URL: Repository, https://github.com/monim67/django-flatpickr
